samABPhfunction/__init__.py
samABPhfunction/conservativepotential.py
samABPhfunction/effectivepotentials.py
samABPhfunction/wfuncsoft.py
samABPhfunction-0.0.4.dist-info/LICENSE
samABPhfunction-0.0.4.dist-info/METADATA
samABPhfunction-0.0.4.dist-info/WHEEL
samABPhfunction-0.0.4.dist-info/top_level.txt
samABPhfunction-0.0.4.dist-info/RECORD
