Metadata-Version: 2.1
Name: samABPhfunction
Version: 0.0.4
Summary: h function (similar to Hamiltonian) for steady-state ABPs
Home-page: https://github.com/samueljmcameron/samABPhfunction
Author: Sam Cameron
Author-email: samuel.j.m.cameron@gmail.com
License: UNKNOWN
Platform: UNKNOWN
Classifier: Programming Language :: Python :: 3
Classifier: License :: OSI Approved :: GNU General Public License v3 (GPLv3)
Classifier: Operating System :: OS Independent
Requires-Python: >=3.6
Requires-Dist: samspecialfuncs (>=0.0.5)
Requires-Dist: numpy
Requires-Dist: scipy
